TrendSignalIndicator/TrendTrader.py
TrendSignalIndicator/_init_.py
CoreIndicators-1.0.5.dist-info/LICENSE
CoreIndicators-1.0.5.dist-info/METADATA
CoreIndicators-1.0.5.dist-info/WHEEL
CoreIndicators-1.0.5.dist-info/top_level.txt
CoreIndicators-1.0.5.dist-info/RECORD
